.gitignore
CHANGES.rst
README.rst
bootstrap.py
buildout.cfg
plone.cfg
setup.cfg
setup.py
docs/HISTORY.txt
docs/INSTALL.txt
docs/LICENSE.GPL
docs/LICENSE.txt
on/__init__.py
on.video.egg-info/PKG-INFO
on.video.egg-info/SOURCES.txt
on.video.egg-info/dependency_links.txt
on.video.egg-info/entry_points.txt
on.video.egg-info/namespace_packages.txt
on.video.egg-info/not-zip-safe
on.video.egg-info/requires.txt
on.video.egg-info/top_level.txt
on/video/INTEGRATION.txt
on/video/__init__.py
on/video/addvideos.py
on/video/config.py
on/video/configuration.py
on/video/configure.zcml
on/video/permissions.zcml
on/video/setuphandlers.py
on/video/testing.py
on/video/version.txt
on/video/video.py
on/video/browser/__init__.py
on/video/browser/configure.zcml
on/video/browser/featuredportlet.py
on/video/browser/featuredvideos.pt
on/video/browser/videogallery.py
on/video/browser/videogallery_templates/videogallery.pt
on/video/locales/README.txt
on/video/profiles/default/controlpanel.xml
on/video/profiles/default/cssregistry.xml
on/video/profiles/default/metadata.xml
on/video/profiles/default/on.video-setup.txt
on/video/profiles/default/portlets.xml
on/video/profiles/default/registry.xml
on/video/profiles/default/types.xml
on/video/profiles/default/types/Collection.xml
on/video/profiles/default/types/Folder.xml
on/video/profiles/default/types/on.video.Video.xml
on/video/static/README.txt
on/video/static/gallery.png
on/video/static/invalidmetafile.png
on/video/static/nometafile.png
on/video/static/nothumbnail.png
on/video/static/novideo.png
on/video/static/video.png
on/video/static/videolisting.css
on/video/tests/Vincent_Untz.metadata
on/video/tests/__init__.py
on/video/tests/corrupted1.metadata
on/video/tests/corrupted2.metadata
on/video/tests/sample_video_1.metadata
on/video/tests/sample_video_1.mp4
on/video/tests/sample_video_1_big.ogv
on/video/tests/sample_video_1_medium.ogv
on/video/tests/sample_video_2.avi
on/video/tests/sample_video_2.metadata
on/video/tests/sample_video_2.mp4
on/video/tests/sample_video_3.metadata
on/video/tests/sample_video_3.mp4
on/video/tests/sample_video_3_medium.ogv
on/video/tests/sample_video_4.metadata
on/video/tests/sample_video_5.metadata
on/video/tests/sample_video_6.metadata
on/video/tests/sample_video_7.metadata
