Metadata-Version: 1.1
Name: on.video
Version: 0.2.2
Summary: dynamic display of video files
Home-page: http://www.oeko.net/
Author: oeko.net mueller & brandt gbr
Author-email: support@oeko.net
License: GPLv3
Keywords: plone video dexterity
Platform: UNKNOWN
Classifier: Framework :: Plone
Classifier: Topic :: Multimedia :: Video
Classifier: Programming Language :: Python
Classifier: Topic :: Software Development :: Libraries :: Python Modules
